fluidkit/__init__.py
fluidkit/core/__init__.py
fluidkit/core/autodiscovery.py
fluidkit/core/config.py
fluidkit/core/constants.py
fluidkit/core/integrator.py
fluidkit/core/schema.py
fluidkit/core/type_conversion.py
fluidkit/core/utils.py
fluidkit/generators/__init__.py
fluidkit/generators/javascript/__init__.py
fluidkit/generators/typescript/__init__.py
fluidkit/generators/typescript/imports.py
fluidkit/generators/typescript/interfaces.py
fluidkit/generators/typescript/pipeline.py
fluidkit/generators/typescript/clients/__init__.py
fluidkit/generators/typescript/clients/fetch.py
fluidkit/generators/typescript/clients/streaming.py
fluidkit/generators/typescript/clients/utils.py
fluidkit/generators/typescript/clients/utils_tests.py
fluidkit/generators/zod/__init__.py
fluidkit/introspection/__init__.py
fluidkit/introspection/models.py
fluidkit/introspection/parameters.py
fluidkit/introspection/routes.py
fluidkit/introspection/security.py
fluidkit-0.2.9.dist-info/METADATA
fluidkit-0.2.9.dist-info/WHEEL
fluidkit-0.2.9.dist-info/top_level.txt
fluidkit-0.2.9.dist-info/RECORD
