Metadata-Version: 2.4
Name: fluidkit
Version: 0.2.9
Summary: Automatic TypeScript client generation for FastAPI through runtime introspection
Author-email: Aswanth Manoj <aswanthmanoj51@gmail.com>
License: MIT
Project-URL: Homepage, https://github.com/AswanthManoj/Fluidkit
Project-URL: Repository, https://github.com/AswanthManoj/Fluidkit
Project-URL: Issues, https://github.com/AswanthManoj/Fluidkit/issues
Project-URL: Documentation, https://github.com/AswanthManoj/Fluidkit#readme
Keywords: fastapi,typescript,code-generation,full-stack,type-safety,sveltekit,nextjs,nuxtjs
Classifier: Development Status :: 4 - Beta
Classifier: Intended Audience :: Developers
Classifier: License :: OSI Approved :: MIT License
Classifier: Programming Language :: Python :: 3
Classifier: Programming Language :: Python :: 3.8
Classifier: Programming Language :: Python :: 3.9
Classifier: Programming Language :: Python :: 3.10
Classifier: Programming Language :: Python :: 3.11
Classifier: Programming Language :: Python :: 3.12
Classifier: Topic :: Software Development :: Code Generators
Classifier: Topic :: Software Development :: Libraries :: Python Modules
Requires-Python: >=3.10
Provides-Extra: dev
Requires-Dist: fastapi[standard]>=0.115.14; extra == "dev"
Requires-Dist: pydantic-extra-types>=2.10.5; extra == "dev"
Requires-Dist: pydantic[email]>=2.11.7; extra == "dev"
Requires-Dist: sse-starlette>=3.0.0; extra == "dev"
Requires-Dist: uvicorn>=0.35.0; extra == "dev"
